kbInterface.py
kbInterface-0.1.1.dist-info/DESCRIPTION.rst
kbInterface-0.1.1.dist-info/METADATA
kbInterface-0.1.1.dist-info/RECORD
kbInterface-0.1.1.dist-info/WHEEL
kbInterface-0.1.1.dist-info/dependency_links.txt
kbInterface-0.1.1.dist-info/metadata.json
kbInterface-0.1.1.dist-info/top_level.txt
