Metadata-Version: 2.0
Name: kbInterface
Version: 0.1.1
Summary: Get KBase Session
Home-page: https://www.github.com/SysBio/kbInterface/
Author: Daniel Hermansson
Author-email: hedani@chalmers.se
License: MIT
Keywords: systems biology research infrastructure
Platform: UNKNOWN
Classifier: Development Status :: 3 - Alpha
Classifier: Intended Audience :: Science/Research
Classifier: Topic :: Scientific/Engineering :: Bio-Informatics
Classifier: License :: OSI Approved :: MIT License
Classifier: Programming Language :: Python :: 2
Classifier: Programming Language :: Python :: 2.6
Classifier: Programming Language :: Python :: 2.7
Requires-Dist: doekbase-data-api (>=0.1.0)
Requires-Dist: requests
